{
  "version": "0.0.0",
  "name": "multi_sig",
  "instructions": [
    {
      "name": "createTransferRequest",
      "accounts": [
        {
          "name": "transferAccount",
          "isMut": true,
          "isSigner": true
        },
        {
          "name": "user",
          "isMut": true,
          "isSigner": true
        },
        {
          "name": "systemProgram",
          "isMut": false,
          "isSigner": false
        }
      ],
      "args": [
        {
          "name": "from",
          "type": "publicKey"
        },
        {
          "name": "to",
          "type": "publicKey"
        },
        {
          "name": "value",
          "type": "u64"
        }
      ]
    },
    {
      "name": "addTransferRequest",
      "accounts": [
        {
          "name": "transferAccount",
          "isMut": true,
          "isSigner": false
        }
      ],
      "args": [
        {
          "name": "from",
          "type": "publicKey"
        },
        {
          "name": "to",
          "type": "publicKey"
        },
        {
          "name": "value",
          "type": "u64"
        }
      ]
    },
    {
      "name": "sendTransferRequest",
      "accounts": [
        {
          "name": "transferAccount",
          "isMut": true,
          "isSigner": false
        }
      ],
      "args": [
        {
          "name": "from",
          "type": "publicKey"
        },
        {
          "name": "index",
          "type": "u64"
        }
      ]
    },
    {
      "name": "declineTransferRequest",
      "accounts": [
        {
          "name": "transferAccount",
          "isMut": true,
          "isSigner": false
        }
      ],
      "args": [
        {
          "name": "from",
          "type": "publicKey"
        },
        {
          "name": "index",
          "type": "u64"
        }
      ]
    },
    {
      "name": "createAirdropRequest",
      "accounts": [
        {
          "name": "airdropAccount",
          "isMut": true,
          "isSigner": true
        },
        {
          "name": "user",
          "isMut": true,
          "isSigner": true
        },
        {
          "name": "systemProgram",
          "isMut": false,
          "isSigner": false
        }
      ],
      "args": [
        {
          "name": "list",
          "type": {
            "vec": {
              "defined": "AirdropRequestStruct"
            }
          }
        }
      ]
    },
    {
      "name": "sendTransferListRequest",
      "accounts": [
        {
          "name": "transferAccount",
          "isMut": true,
          "isSigner": false
        }
      ],
      "args": [
        {
          "name": "from",
          "type": "publicKey"
        },
        {
          "name": "items",
          "type": {
            "vec": "u64"
          }
        }
      ]
    },
    {
      "name": "declineTransferListRequest",
      "accounts": [
        {
          "name": "transferAccount",
          "isMut": true,
          "isSigner": false
        }
      ],
      "args": [
        {
          "name": "from",
          "type": "publicKey"
        },
        {
          "name": "items",
          "type": {
            "vec": "u64"
          }
        }
      ]
    },
    {
      "name": "sendAirdropListRequest",
      "accounts": [
        {
          "name": "airdropAccount",
          "isMut": true,
          "isSigner": false
        }
      ],
      "args": [
        {
          "name": "list",
          "type": {
            "vec": {
              "defined": "AirdropRequestStruct"
            }
          }
        }
      ]
    }
  ],
  "accounts": [
    {
      "name": "RequestStructList",
      "type": {
        "kind": "struct",
        "fields": [
          {
            "name": "list",
            "type": {
              "vec": {
                "defined": "RequestStruct"
              }
            }
          }
        ]
      }
    },
    {
      "name": "AirdropRequestStructList",
      "type": {
        "kind": "struct",
        "fields": [
          {
            "name": "list",
            "type": {
              "vec": {
                "defined": "AirdropRequestStruct"
              }
            }
          }
        ]
      }
    }
  ],
  "types": [
    {
      "name": "RequestStruct",
      "type": {
        "kind": "struct",
        "fields": [
          {
            "name": "isActived",
            "type": "bool"
          },
          {
            "name": "isClosed",
            "type": "bool"
          },
          {
            "name": "isSent",
            "type": "bool"
          },
          {
            "name": "createdBy",
            "type": "publicKey"
          },
          {
            "name": "dealedBy",
            "type": "publicKey"
          },
          {
            "name": "to",
            "type": "publicKey"
          },
          {
            "name": "value",
            "type": "u64"
          },
          {
            "name": "index",
            "type": "u64"
          }
        ]
      }
    },
    {
      "name": "AirdropRequestStruct",
      "type": {
        "kind": "struct",
        "fields": [
          {
            "name": "address",
            "type": "publicKey"
          },
          {
            "name": "balance",
            "type": "u64"
          }
        ]
      }
    }
  ],
  "metadata": {
    "address": "AeQu2eRKfoDp45vHCVvQiDWuDkw6gLJ12WUXimNHfayo"
  }
}